<annotation>
	<folder>malignant</folder>
	<filename>malignant103.jpg</filename>
	<path>C:\Users\LinziGoooosh\Documents\ex5\ope\malignant\malignant103.jpg</path>
	<source>
		<database>Unknown</database>
	</source>
	<size>
		<width>555</width>
		<height>488</height>
		<depth>3</depth>
	</size>
	<segmented>0</segmented>
	<object>
		<name>malignant</name>
		<pose>Unspecified</pose>
		<truncated>0</truncated>
		<difficult>0</difficult>
		<bndbox>
			<xmin>101</xmin>
			<ymin>72</ymin>
			<xmax>360</xmax>
			<ymax>360</ymax>
		</bndbox>
	</object>
</annotation>